<?xml version="1.0" encoding="utf-8" ?>
<TypeLobbies>
  <TypeLobby>
    <Name>8 игроков</Name>
    <QuantityPlayers>8</QuantityPlayers>
    <DurabilityCastle>10</DurabilityCastle>
    <Gold>8000</Gold>
    <MaxHeroes>49</MaxHeroes>
    <DayStartTournament>10</DayStartTournament>
    <StartPointConstructionGuild>2</StartPointConstructionGuild>
    <StartPointConstructionEconomic>2</StartPointConstructionEconomic>
    <PointConstructionGuildPerDay>1</PointConstructionGuildPerDay>
    <PointConstructionEconomicPerDay>1</PointConstructionEconomicPerDay>
  </TypeLobby>
</TypeLobbies>